Metadata-Version: 2.1
Name: getwebtitle
Version: 0.0.3
Summary: A function to get a website title
Home-page: https://github.com/suifengpiaoyang/packagingLearning
Author: Zhang
Author-email: secret@xxx.com
License: GPL
Download-URL: https://github.com/suifengpiaoyang/packagingLearning/archive/master.zip
Platform: UNKNOWN
Classifier: Programming Language :: Python
Classifier: Programming Language :: Python :: 3
Classifier: Programming Language :: Python :: 3.5
Classifier: License :: OSI Approved :: GNU General Public License v3 (GPLv3)
